tailwind_sql/__init__.py
tailwind_sql/main.py
tailwind_sql/prompts.py
tailwind_sql-2025.12.21155143.dist-info/METADATA
tailwind_sql-2025.12.21155143.dist-info/WHEEL
tailwind_sql-2025.12.21155143.dist-info/top_level.txt
tailwind_sql-2025.12.21155143.dist-info/RECORD
