Metadata-Version: 2.4
Name: tailwind-sql
Version: 2025.12.21155143
Summary: A new package that allows users to write SQL queries using a simplified, Tailwind CSS-like syntax. It takes natural language or abbreviated input from the user and converts it into valid, structured S
Author-email: tailwind-sql <hi@eugene.plus>
License: MIT
Project-URL: Homepage, https://github.com/chigwell/tailwind-sql
Requires-Python: >=3.9
Requires-Dist: langchain-llm7>=0.0.0
Requires-Dist: llmatch-messages>=0.0.0
Requires-Dist: langchain-core>=0.3.0
